[
    {"n": "Igname", "p": 1200, "u": "tubercule", "c": "Féculents"},
    {"n": "Farine de maïs", "p": 500, "u": "kg", "c": "Féculents"},
    {"n": "Farine de riz", "p": 800, "u": "kg", "c": "Féculents"},
    {"n": "Pâte de maïs fermentée", "p": 300, "u": "kg", "c": "Féculents"},
    {"n": "Riz", "p": 600, "u": "kg", "c": "Féculents"},
    {"n": "Couscous", "p": 1000, "u": "paquet", "c": "Féculents"},
    {"n": "Spaghetti", "p": 400, "u": "paquet", "c": "Féculents"},
    {"n": "Banane Plantain", "p": 1000, "u": "tas", "c": "Féculents"},
    {"n": "Haricot", "p": 900, "u": "kg", "c": "Féculents"},
    {"n": "Attiéké", "p": 250, "u": "boule", "c": "Féculents"},
    {"n": "Gari", "p": 450, "u": "kg", "c": "Féculents"},
    {"n": "Tapioca", "p": 700, "u": "kg", "c": "Féculents"},
    {"n": "Fonio", "p": 1200, "u": "kg", "c": "Féculents"},
    {"n": "Viande de Poulet", "p": 4500, "u": "unité", "c": "Viandes"},
    {"n": "Viande de Boeuf", "p": 3500, "u": "kg", "c": "Viandes"},
    {"n": "Viande de Mouton", "p": 4500, "u": "kg", "c": "Viandes"},
    {"n": "Peau de boeuf (Akpame)", "p": 500, "u": "tas", "c": "Viandes"},
    {"n": "Oeuf", "p": 100, "u": "unité", "c": "Viandes"},
    {"n": "Abats de Boeuf", "p": 2000, "u": "kg", "c": "Viandes"},
    {"n": "Poisson Capitaine", "p": 4000, "u": "kg", "c": "Poissons"},
    {"n": "Poisson fumé (Akpalan)", "p": 500, "u": "unité", "c": "Poissons"},
    {"n": "Petit poisson (Deuevi)", "p": 200, "u": "tas", "c": "Poissons"},
    {"n": "Poisson frit (Kanami)", "p": 600, "u": "unité", "c": "Poissons"},
    {"n": "Crabe (Aglan)", "p": 1500, "u": "tas", "c": "Poissons"},
    {"n": "Crevettes fraîches", "p": 3000, "u": "kg", "c": "Poissons"},
    {"n": "Crevettes séchées", "p": 500, "u": "verre", "c": "Poissons"},
    {"n": "Sardine en boite", "p": 600, "u": "boite", "c": "Poissons"},
    {"n": "Tomate Fraiche", "p": 500, "u": "kg", "c": "Légumes"},
    {"n": "Oignon Galmi", "p": 450, "u": "kg", "c": "Légumes"},
    {"n": "Gombo frais (Fétri)", "p": 300, "u": "tas", "c": "Légumes"},
    {"n": "Gombo sec", "p": 400, "u": "tas", "c": "Légumes"},
    {"n": "Chou", "p": 500, "u": "unité", "c": "Légumes"},
    {"n": "Carotte", "p": 200, "u": "tas", "c": "Légumes"},
    {"n": "Concombre", "p": 200, "u": "unité", "c": "Légumes"},
    {"n": "Laitue", "p": 500, "u": "pied", "c": "Légumes"},
    {"n": "Beterave", "p": 300, "u": "tas", "c": "Légumes"},
    {"n": "Feuille de Gboma", "p": 200, "u": "attache", "c": "Légumes"},
    {"n": "Feuille d'Adémé", "p": 200, "u": "attache", "c": "Légumes"},
    {"n": "Feuille de Gnatou", "p": 200, "u": "attache", "c": "Légumes"},
    {"n": "Feuille de Baobab", "p": 200, "u": "attache", "c": "Légumes"},
    {"n": "Huile Végétale", "p": 1200, "u": "L", "c": "Épicerie"},
    {"n": "Huile de Palme", "p": 1100, "u": "L", "c": "Épicerie"},
    {"n": "Pâte d'Arachide", "p": 500, "u": "pot", "c": "Épicerie"},
    {"n": "Graine de courge (Goussi)", "p": 1000, "u": "bol", "c": "Épicerie"},
    {"n": "Tomate Concentrée", "p": 150, "u": "boite", "c": "Épicerie"},
    {"n": "Sucre", "p": 800, "u": "kg", "c": "Épicerie"},
    {"n": "Lait liquide", "p": 2000, "u": "boite", "c": "Épicerie"},
    {"n": "Lait en poudre", "p": 150, "u": "sachet", "c": "Épicerie"},
    {"n": "Levure boulanger", "p": 150, "u": "sachet", "c": "Épicerie"},
    {"n": "Mayonnaise", "p": 1500, "u": "bocal", "c": "Épicerie"},
    {"n": "Vinaigre", "p": 600, "u": "bouteille", "c": "Épicerie"},
    {"n": "Pain Baguette", "p": 150, "u": "unité", "c": "Épicerie"},
    {"n": "Ail", "p": 100, "u": "tas", "c": "Épices"},
    {"n": "Gingembre", "p": 100, "u": "tas", "c": "Épices"},
    {"n": "Piment frais", "p": 200, "u": "tas", "c": "Épices"},
    {"n": "Piment en poudre", "p": 100, "u": "sachet", "c": "Épices"},
    {"n": "Sel Iodé", "p": 250, "u": "sachet", "c": "Épices"},
    {"n": "Cube bouillon", "p": 25, "u": "unité", "c": "Épices"},
    {"n": "Potasse", "p": 50, "u": "unité", "c": "Épices"},
    {"n": "Afiti (Moutarde locale)", "p": 100, "u": "boule", "c": "Épices"},
    {"n": "Poivre noir", "p": 100, "u": "sachet", "c": "Épices"}
]
